dbox_filesync.py
dbox_filesync-0.3.dist-info/DESCRIPTION.rst
dbox_filesync-0.3.dist-info/METADATA
dbox_filesync-0.3.dist-info/RECORD
dbox_filesync-0.3.dist-info/WHEEL
dbox_filesync-0.3.dist-info/metadata.json
dbox_filesync-0.3.dist-info/top_level.txt
